utilities/__init__.py
utilities/attoIDS3010.py
utilities/database.py
utilities/environment.py
utilities/knowles.py
utilities/modOp.py
utilities/numatoLabRL002.py
utilities/operatorManualSetup.py
utilities/picoscope.py
utilities/pressureControl.py
utilities/ps4000a.py
utilities/zaberLRQ600.py
utilities/zaberLRQ600XYZ.py
utilities/zaberLRQ600YZ.py
utilities/zaberLSQ150.py
utilities/pythonArchive/__init__.py
utilities/pythonArchive/garchive.py
cmtqoutilities-0.6.0.dist-info/METADATA
cmtqoutilities-0.6.0.dist-info/WHEEL
cmtqoutilities-0.6.0.dist-info/top_level.txt
cmtqoutilities-0.6.0.dist-info/RECORD
