Metadata-Version: 2.4
Name: cmtqoutilities
Version: 0.6.0
Summary: API for all cmtqo devices
Home-page: https://gitlab.phys.ethz.ch/code/experiment/mm-runexperiment
Author: Sebastian Huber
Author-email: huberse@phys.ethz.ch
Requires-Python: >=3.8
Requires-Dist: numpy>=1.18.0
Requires-Dist: requests>=2.25.0
Requires-Dist: scipy>=1.5.0
Requires-Dist: pyserial>=3.5
Requires-Dist: zaber.serial>=0.9
Requires-Dist: pymysql>=1.1.1
Requires-Dist: nbconvert>=7.0.0
Requires-Dist: nbformat>=5.0.0
Requires-Dist: jupyter>=1.1.1
Dynamic: author
Dynamic: author-email
Dynamic: description
Dynamic: description-content-type
Dynamic: home-page
Dynamic: requires-dist
Dynamic: requires-python
Dynamic: summary
